can_cannelloni/__init__.py
can_cannelloni/bus.py
can_cannelloni/protocol.py
can_cannelloni-0.1.0.dist-info/licenses/LICENSE
can_cannelloni-0.1.0.dist-info/METADATA
can_cannelloni-0.1.0.dist-info/WHEEL
can_cannelloni-0.1.0.dist-info/entry_points.txt
can_cannelloni-0.1.0.dist-info/top_level.txt
can_cannelloni-0.1.0.dist-info/RECORD
